c41811/config/__init__.py
c41811/config/_protocols.py
c41811/config/_version.py
c41811/config/abc.py
c41811/config/errors.py
c41811/config/lazy_import.py
c41811/config/main.py
c41811/config/path.py
c41811/config/py.typed
c41811/config/safe_writer.py
c41811/config/utils.py
c41811/config/validators.py
c41811/config/basic/__init__.py
c41811/config/basic/_generate_operators.py
c41811/config/basic/component.py
c41811/config/basic/core.py
c41811/config/basic/environment.py
c41811/config/basic/factory.py
c41811/config/basic/jproperties.py
c41811/config/basic/mapping.py
c41811/config/basic/number.py
c41811/config/basic/object.py
c41811/config/basic/sequence.py
c41811/config/basic/utils.py
c41811/config/processor/__init__.py
c41811/config/processor/cbor2.py
c41811/config/processor/component.py
c41811/config/processor/hjson.py
c41811/config/processor/jproperties.py
c41811/config/processor/json.py
c41811/config/processor/os_env.py
c41811/config/processor/pickle.py
c41811/config/processor/plaintext.py
c41811/config/processor/python.py
c41811/config/processor/python_literal.py
c41811/config/processor/pyyaml.py
c41811/config/processor/rtoml.py
c41811/config/processor/ruamel_yaml.py
c41811/config/processor/tarfile.py
c41811/config/processor/tomlkit.py
c41811/config/processor/zipfile.py
c41811_config-0.3.1.dist-info/licenses/LICENSE
c41811_config-0.3.1.dist-info/METADATA
c41811_config-0.3.1.dist-info/WHEEL
c41811_config-0.3.1.dist-info/top_level.txt
c41811_config-0.3.1.dist-info/RECORD
