Metadata-Version: 2.4
Name: C41811.Config
Version: 0.3.1
Summary: Simplifies config management with flexible API and formats.
Author-email: C418____11 <C418-11@qq.com>
License-Expression: MIT
Project-URL: Bug Tracker, https://github.com/C418-11/C41811_Config/issues
Project-URL: Source Code, https://github.com/C418-11/C41811_Config
Project-URL: Documentation, https://C41811Config.readthedocs.io
Keywords: config,yaml,toml,json
Classifier: Development Status :: 3 - Alpha
Classifier: Intended Audience :: Developers
Classifier: Natural Language :: Chinese (Simplified)
Classifier: Operating System :: OS Independent
Classifier: Programming Language :: Python
Classifier: Programming Language :: Python :: 3
Classifier: Programming Language :: Python :: 3 :: Only
Classifier: Programming Language :: Python :: 3.12
Classifier: Programming Language :: Python :: 3.13
Classifier: Programming Language :: Python :: 3.14
Classifier: Programming Language :: Python :: Free Threading
Classifier: Programming Language :: Python :: Implementation :: CPython
Classifier: Topic :: Software Development :: Libraries :: Application Frameworks
Classifier: Topic :: Software Development :: Libraries :: Python Modules
Classifier: Typing :: Typed
Requires-Python: >=3.12
License-File: LICENSE
Requires-Dist: pydantic<2.13.0,>=2.11.1
Requires-Dist: wrapt~=2.0.0
Requires-Dist: portalocker<3.3.0,>=3.1.1
Requires-Dist: mypy-extensions<1.2,>=1.0
Provides-Extra: dev
Requires-Dist: PyYAML~=6.0.2; extra == "dev"
Requires-Dist: ruamel.yaml~=0.18.10; extra == "dev"
Requires-Dist: rtoml<0.14,>=0.12; extra == "dev"
Requires-Dist: tomlkit~=0.13.3; extra == "dev"
Requires-Dist: cbor2~=5.7.0; extra == "dev"
Requires-Dist: jproperties~=2.1.2; extra == "dev"
Requires-Dist: hjson~=3.1.0; extra == "dev"
Requires-Dist: tox<4.33,>=4.26; extra == "dev"
Requires-Dist: pre-commit<4.6,>=4.2; extra == "dev"
Provides-Extra: pyyamlsl
Requires-Dist: PyYAML~=6.0.2; extra == "pyyamlsl"
Provides-Extra: ruamelyamlsl
Requires-Dist: ruamel.yaml~=0.18.10; extra == "ruamelyamlsl"
Provides-Extra: rtomlsl
Requires-Dist: rtoml<0.14,>=0.12; extra == "rtomlsl"
Provides-Extra: tomlkitsl
Requires-Dist: tomlkit~=0.13.3; extra == "tomlkitsl"
Provides-Extra: cbor2sl
Requires-Dist: cbor2~=5.7.0; extra == "cbor2sl"
Provides-Extra: jpropertiessl
Requires-Dist: jproperties~=2.1.2; extra == "jpropertiessl"
Provides-Extra: hjsonsl
Requires-Dist: hjson~=3.1.0; extra == "hjsonsl"
Dynamic: license-file
